{
    "description": "",
    "tags": [
        {
            "id": 118620538,
            "tagId": 30143178,
            "name": "train",
            "value": null,
            "labelerLogin": "fsocov2",
            "createdAt": "2021-06-29T08:08:12.319Z",
            "updatedAt": "2021-06-29T08:08:12.319Z"
        }
    ],
    "size": {
        "height": 1360,
        "width": 2200
    },
    "objects": [
        {
            "id": 890091407,
            "classId": 9993506,
            "description": "",
            "geometryType": "rectangle",
            "labelerLogin": "fsocov2",
            "createdAt": "2021-06-29T08:06:11.544Z",
            "updatedAt": "2021-06-29T08:06:11.544Z",
            "tags": [],
            "classTitle": "yellow_cone",
            "points": {
                "exterior": [
                    [
                        1936,
                        750
                    ],
                    [
                        2040,
                        858
                    ]
                ],
                "interior": []
            }
        },
        {
            "id": 890091406,
            "classId": 9993512,
            "description": "",
            "geometryType": "rectangle",
            "labelerLogin": "fsocov2",
            "createdAt": "2021-06-29T08:06:11.544Z",
            "updatedAt": "2021-06-29T08:06:11.544Z",
            "tags": [],
            "classTitle": "orange_cone",
            "points": {
                "exterior": [
                    [
                        1602,
                        834
                    ],
                    [
                        1770,
                        1026
                    ]
                ],
                "interior": []
            }
        },
        {
            "id": 890091405,
            "classId": 9993512,
            "description": "",
            "geometryType": "rectangle",
            "labelerLogin": "fsocov2",
            "createdAt": "2021-06-29T08:06:11.544Z",
            "updatedAt": "2021-06-29T08:06:11.544Z",
            "tags": [
                {
                    "id": 135995062,
                    "tagId": 30143182,
                    "name": "truncated",
                    "value": null,
                    "labelerLogin": "fsocov2",
                    "createdAt": "2021-06-29T08:06:11.546Z",
                    "updatedAt": "2021-06-29T08:06:11.546Z"
                }
            ],
            "classTitle": "orange_cone",
            "points": {
                "exterior": [
                    [
                        1639,
                        744
                    ],
                    [
                        1721,
                        842
                    ]
                ],
                "interior": []
            }
        },
        {
            "id": 890091404,
            "classId": 9993511,
            "description": "",
            "geometryType": "rectangle",
            "labelerLogin": "fsocov2",
            "createdAt": "2021-06-29T08:06:11.544Z",
            "updatedAt": "2021-06-29T08:06:11.544Z",
            "tags": [],
            "classTitle": "blue_cone",
            "points": {
                "exterior": [
                    [
                        1334,
                        838
                    ],
                    [
                        1485,
                        1014
                    ]
                ],
                "interior": []
            }
        },
        {
            "id": 890091403,
            "classId": 9993513,
            "description": "",
            "geometryType": "rectangle",
            "labelerLogin": "fsocov2",
            "createdAt": "2021-06-29T08:06:11.544Z",
            "updatedAt": "2021-06-29T08:06:11.544Z",
            "tags": [],
            "classTitle": "large_orange_cone",
            "points": {
                "exterior": [
                    [
                        1401,
                        696
                    ],
                    [
                        1499,
                        822
                    ]
                ],
                "interior": []
            }
        },
        {
            "id": 890091402,
            "classId": 9993513,
            "description": "",
            "geometryType": "rectangle",
            "labelerLogin": "fsocov2",
            "createdAt": "2021-06-29T08:06:11.544Z",
            "updatedAt": "2021-06-29T08:06:11.544Z",
            "tags": [],
            "classTitle": "large_orange_cone",
            "points": {
                "exterior": [
                    [
                        1334,
                        696
                    ],
                    [
                        1414,
                        816
                    ]
                ],
                "interior": []
            }
        },
        {
            "id": 890091401,
            "classId": 9993512,
            "description": "",
            "geometryType": "rectangle",
            "labelerLogin": "fsocov2",
            "createdAt": "2021-06-29T08:06:11.544Z",
            "updatedAt": "2021-06-29T08:06:11.544Z",
            "tags": [],
            "classTitle": "orange_cone",
            "points": {
                "exterior": [
                    [
                        1241,
                        740
                    ],
                    [
                        1299,
                        812
                    ]
                ],
                "interior": []
            }
        },
        {
            "id": 890091400,
            "classId": 9993506,
            "description": "",
            "geometryType": "rectangle",
            "labelerLogin": "fsocov2",
            "createdAt": "2021-06-29T08:06:11.544Z",
            "updatedAt": "2021-06-29T08:06:11.544Z",
            "tags": [
                {
                    "id": 135995061,
                    "tagId": 30143182,
                    "name": "truncated",
                    "value": null,
                    "labelerLogin": "fsocov2",
                    "createdAt": "2021-06-29T08:06:11.546Z",
                    "updatedAt": "2021-06-29T08:06:11.546Z"
                }
            ],
            "classTitle": "yellow_cone",
            "points": {
                "exterior": [
                    [
                        1150,
                        740
                    ],
                    [
                        1202,
                        808
                    ]
                ],
                "interior": []
            }
        },
        {
            "id": 890091399,
            "classId": 9993512,
            "description": "",
            "geometryType": "rectangle",
            "labelerLogin": "fsocov2",
            "createdAt": "2021-06-29T08:06:11.544Z",
            "updatedAt": "2021-06-29T08:06:11.544Z",
            "tags": [],
            "classTitle": "orange_cone",
            "points": {
                "exterior": [
                    [
                        1158,
                        800
                    ],
                    [
                        1264,
                        936
                    ]
                ],
                "interior": []
            }
        },
        {
            "id": 890091398,
            "classId": 9993512,
            "description": "",
            "geometryType": "rectangle",
            "labelerLogin": "fsocov2",
            "createdAt": "2021-06-29T08:06:11.544Z",
            "updatedAt": "2021-06-29T08:06:11.544Z",
            "tags": [],
            "classTitle": "orange_cone",
            "points": {
                "exterior": [
                    [
                        869,
                        894
                    ],
                    [
                        1065,
                        1126
                    ]
                ],
                "interior": []
            }
        },
        {
            "id": 890091397,
            "classId": 9993513,
            "description": "",
            "geometryType": "rectangle",
            "labelerLogin": "fsocov2",
            "createdAt": "2021-06-29T08:06:11.544Z",
            "updatedAt": "2021-06-29T08:06:11.544Z",
            "tags": [
                {
                    "id": 135995060,
                    "tagId": 30143182,
                    "name": "truncated",
                    "value": null,
                    "labelerLogin": "fsocov2",
                    "createdAt": "2021-06-29T08:06:11.546Z",
                    "updatedAt": "2021-06-29T08:06:11.546Z"
                }
            ],
            "classTitle": "large_orange_cone",
            "points": {
                "exterior": [
                    [
                        958,
                        729
                    ],
                    [
                        988,
                        766
                    ]
                ],
                "interior": []
            }
        },
        {
            "id": 890091396,
            "classId": 9993513,
            "description": "",
            "geometryType": "rectangle",
            "labelerLogin": "fsocov2",
            "createdAt": "2021-06-29T08:06:11.544Z",
            "updatedAt": "2021-06-29T08:06:11.544Z",
            "tags": [
                {
                    "id": 135995059,
                    "tagId": 30143182,
                    "name": "truncated",
                    "value": null,
                    "labelerLogin": "fsocov2",
                    "createdAt": "2021-06-29T08:06:11.546Z",
                    "updatedAt": "2021-06-29T08:06:11.546Z"
                }
            ],
            "classTitle": "large_orange_cone",
            "points": {
                "exterior": [
                    [
                        904,
                        728
                    ],
                    [
                        929,
                        761
                    ]
                ],
                "interior": []
            }
        }
    ]
}